htr_iiif_claude/.idea/.gitignore
htr_iiif_claude/.idea/LNKD.tech Editor.xml
htr_iiif_claude/.idea/htr_iiif_claude.iml
htr_iiif_claude/.idea/inspectionProfiles/profiles_settings.xml
htr_iiif_claude/.idea/misc.xml
htr_iiif_claude/.idea/modules.xml
htr_iiif_claude/.idea/vcs.xml
htr_iiif_claude/1983toc1.json
htr_iiif_claude/1983toc2.json
htr_iiif_claude/1984toc1.json
htr_iiif_claude/1984toc2.json
htr_iiif_claude/1985toc1.json
htr_iiif_claude/1985toc2.json
htr_iiif_claude/1985toc3.json
htr_iiif_claude/1986toc1.json
htr_iiif_claude/1986toc2.json
htr_iiif_claude/1987toc1.json
htr_iiif_claude/1987toc2.json
htr_iiif_claude/1988toc1.json
htr_iiif_claude/1988toc2.json
htr_iiif_claude/__init__.py
htr_iiif_claude/claude/__init__.py
htr_iiif_claude/claude/claude.py
htr_iiif_claude/htr.py
htr_iiif_claude/image/__init__.py
htr_iiif_claude/image/image.py
htr_iiif_claude/manifest/__init__.py
htr_iiif_claude/manifest/manifest.py
htr_iiif_claude/output.json
htr_iiif_claude/output.txt
htr_iiif_claude-0.1.3.dist-info/METADATA
htr_iiif_claude-0.1.3.dist-info/WHEEL
htr_iiif_claude-0.1.3.dist-info/entry_points.txt
htr_iiif_claude-0.1.3.dist-info/RECORD
