Metadata-Version: 2.1
Name: htr-iiif-claude
Version: 0.1.3
Summary: Generate HTR from IIIF Resources
License: MIT
Author: Mark Baggett
Author-email: markpbaggett@gmail.com
Requires-Python: >=3.8,<4.0
Classifier: License :: OSI Approved :: MIT License
Classifier: Programming Language :: Python :: 3
Classifier: Programming Language :: Python :: 3.8
Classifier: Programming Language :: Python :: 3.9
Classifier: Programming Language :: Python :: 3.10
Classifier: Programming Language :: Python :: 3.11
Classifier: Programming Language :: Python :: 3.12
Requires-Dist: anthropic (>=0.29.0,<0.30.0)
Requires-Dist: click (>=8.1.7,<9.0.0)
Requires-Dist: httpx (>=0.27.0,<0.28.0)
Requires-Dist: tqdm (>=4.66.4,<5.0.0)
